SystemVerilog/src/mac_seq.sv
// a simple simulation of a sequential MAC (multiply accumulator) gate used in neural networks
module mac_seq(
    input logic clk,
    input logic reset,
    input logic signed [3:0] X,
    input logic signed [3:0] w,
    output logic signed [7:0] acc
);

// combinational multiplier-term

logic signed [7:0] product;
assign product = X * w;

// sequential register (memory)

always_ff @(posedge clk) begin : MAC
    
    if (reset)
        acc <= 0;
    else
        acc <= acc + product;

end

endmodule

SystemVerilog/tb/mac_seq_tb.sv
module mac_seq_tb;

logic clk;
logic reset;
logic signed [3:0] X;
logic signed [3:0] w;
logic signed [7:0] acc;

// Design Under Test (DUT)
mac_seq dut(
    .clk(clk),
    .reset(reset),
    .X(X),
    .w(w),
    .acc(acc)
);

always #5 clk = ~clk; // toggle clock every 5 ns

initial begin

    $dumpfile("mac.vcd");
    $dumpvars(0, mac_seq_tb);

    $monitor("t=%0t | clk=%0d reset=%0d X=%0d w=%0d acc=%0d",
            $time, clk, reset, X, w, acc);
    
    // initialize signals 
    clk = 0;
    reset = 1;
    X = 0;
    w = 0;

    #10; // wait timeline

    // update signals 
    reset = 0;
    X = 2;
    w = 3;

    #50;

    $finish;

end
    
endmodule

SystemVerilog/waves/mac.vcd
$date
	Mon Jun 08 09:37:20 2026
$end
$version
	Icarus Verilog
$end
$timescale
	1s
$end
$scope module mac_seq_tb $end
$var wire 8 ! acc [7:0] $end
$var reg 4 " X [3:0] $end
$var reg 1 # clk $end
$var reg 1 $ reset $end
$var reg 4 % w [3:0] $end
$scope module dut $end
$var wire 4 & X [3:0] $end
$var wire 1 # clk $end
$var wire 1 $ reset $end
$var wire 4 ' w [3:0] $end
$var wire 8 ( product [7:0] $end
$var reg 8 ) acc [7:0] $end
$scope begin MAC $end
$upscope $end
$upscope $end
$upscope $end
$enddefinitions $end
$comment Show the parameter values. $end
$dumpall
$end
#0
$dumpvars
bx )
b0 (
b0 '
b0 &
b0 %
1$
0#
b0 "
bx !
$end
#5
b0 !
b0 )
1#
#10
0#
b110 (
b11 %
b11 '
b10 "
b10 &
0$
#15
b110 !
b110 )
1#
#20
0#
#25
b1100 !
b1100 )
1#
#30
0#
#35
b10010 !
b10010 )
1#
#40
0#
#45
b11000 !
b11000 )
1#
#50
0#
#55
b11110 !
b11110 )
1#
